[{"fields": {"name": "final_grade_iki", "last_consumed_activity_pk": 13704, "label": "Final Grade", "course": 1, "type": "OUT", "num_bins": 10, "polymorphic_ctype": ["stats", "singleeventvariable"]}, "model": "stats.variable", "pk": 1}, {"fields": {"name": "final_grade_leren", "last_consumed_activity_pk": 12750, "label": "Final Grade", "course": 2, "type": "OUT", "num_bins": 10, "polymorphic_ctype": ["stats", "singleeventvariable"]}, "model": "stats.variable", "pk": 2}, {"fields": {"name": "avg_grade_iki", "last_consumed_activity_pk": 13598, "label": "Average Grade", "course": 1, "type": "IN", "num_bins": 10, "polymorphic_ctype": ["stats", "singleeventvariable"]}, "model": "stats.variable", "pk": 3}, {"fields": {"name": "avg_grade_leren", "last_consumed_activity_pk": 12676, "label": "Average Grade", "course": 2, "type": "IN", "num_bins": 10, "polymorphic_ctype": ["stats", "singleeventvariable"]}, "model": "stats.variable", "pk": 4}, {"fields": {"name": "website_time_oop", "last_consumed_activity_pk": 13799, "label": "Time on website", "course": 3, "type": "IN", "num_bins": 10, "polymorphic_ctype": ["stats", "singleeventvariable"]}, "model": "stats.variable", "pk": 5}, {"fields": {"name": "video_time_oop", "last_consumed_activity_pk": 13741, "label": "Time spent watching video", "course": 3, "type": "IN", "num_bins": 10, "polymorphic_ctype": ["stats", "singleeventvariable"]}, "model": "stats.variable", "pk": 6}, {"fields": {"name": "hours_before_compile_oop", "last_consumed_activity_pk": 0, "label": "Aantal uren voordat de problem set is uitgeprobeerd", "course": 3, "type": "IN", "num_bins": 10, "polymorphic_ctype": ["stats", "assignmentlinkedvariable"]}, "model": "stats.variable", "pk": 7}, {"fields": {"name": "hours_before_deadline_submitted_iki", "last_consumed_activity_pk": 0, "label": "Aantal uren voor de deadine dat de opdracht is ingeleverd", "course": 1, "type": "IN", "num_bins": 10, "polymorphic_ctype": ["stats", "assignmentlinkedvariable"]}, "model": "stats.variable", "pk": 8}, {"fields": {"name": "hours_before_deadline_submitted_leren", "last_consumed_activity_pk": 0, "label": "Aantal uren voor de deadine dat de opdracht is ingeleverd", "course": 2, "type": "IN", "num_bins": 10, "polymorphic_ctype": ["stats", "assignmentlinkedvariable"]}, "model": "stats.variable", "pk": 9}, {"fields": {"name": "presence_iki", "last_consumed_activity_pk": 0, "label": "Aantal keer aanwezig geweest", "course": 1, "type": "IN", "num_bins": 10, "polymorphic_ctype": ["stats", "singleeventvariable"]}, "model": "stats.variable", "pk": 10}, {"fields": {"name": "presence_leren", "last_consumed_activity_pk": 0, "label": "Aantal keer aanwezig geweest", "course": 2, "type": "IN", "num_bins": 10, "polymorphic_ctype": ["stats", "singleeventvariable"]}, "model": "stats.variable", "pk": 11}]